{
	"info": {
		"_postman_id": "d7cce504-357e-44e7-a877-94ef46218960",
		"name": "Prueba",
		"schema": "https://schema.getpostman.com/json/collection/v2.1.0/collection.json"
	},
	"item": [
		{
			"name": "CRUD Usuario",
			"item": [
				{
					"name": "GET Usuarios",
					"request": {
						"method": "GET",
						"header": [
							{
								"key": "",
								"value": "",
								"type": "text",
								"disabled": true
							}
						],
						"url": {
							"raw": "http://localhost:9090/usuario",
							"protocol": "http",
							"host": [
								"localhost"
							],
							"port": "9090",
							"path": [
								"usuario"
							]
						}
					},
					"response": []
				},
				{
					"name": "POST Usuarios",
					"request": {
						"method": "POST",
						"header": [],
						"body": {
							"mode": "raw",
							"raw": "{\r\n    \"userName\": \"carlos20\",\r\n\t\"password\": \"1234\",\r\n\t\"realName\": \"Carlos Rodriguez\"\r\n}",
							"options": {
								"raw": {
									"language": "json"
								}
							}
						},
						"url": {
							"raw": "http://localhost:9090/usuario",
							"protocol": "http",
							"host": [
								"localhost"
							],
							"port": "9090",
							"path": [
								"usuario"
							]
						}
					},
					"response": []
				},
				{
					"name": "UPDATE Usuarios",
					"request": {
						"method": "PUT",
						"header": [],
						"body": {
							"mode": "raw",
							"raw": "{\r\n        \"id\": 1,\r\n        \"userName\": \"carlos30\",\r\n        \"password\": \"1234\",\r\n        \"realName\": \"Carlos Rodriguez\"\r\n    }",
							"options": {
								"raw": {
									"language": "json"
								}
							}
						},
						"url": {
							"raw": "http://localhost:9090/usuario",
							"protocol": "http",
							"host": [
								"localhost"
							],
							"port": "9090",
							"path": [
								"usuario"
							]
						}
					},
					"response": []
				},
				{
					"name": "DELETE Usuarios",
					"request": {
						"method": "DELETE",
						"header": [],
						"url": {
							"raw": "http://localhost:9090/usuario/delete/1",
							"protocol": "http",
							"host": [
								"localhost"
							],
							"port": "9090",
							"path": [
								"usuario",
								"delete",
								"1"
							]
						}
					},
					"response": []
				}
			]
		},
		{
			"name": "Security",
			"item": []
		}
	]
}